{"trial_id": "00", "hyperparameters": {"space": [{"class_name": "Int", "config": {"name": "units_1", "default": null, "conditions": [], "min_value": 50, "max_value": 200, "step": 10, "sampling": "linear"}}, {"class_name": "Int", "config": {"name": "units_2", "default": null, "conditions": [], "min_value": 50, "max_value": 200, "step": 10, "sampling": "linear"}}, {"class_name": "Int", "config": {"name": "units_3", "default": null, "conditions": [], "min_value": 50, "max_value": 200, "step": 10, "sampling": "linear"}}, {"class_name": "Choice", "config": {"name": "optimizer", "default": "adam", "conditions": [], "values": ["adam", "rmsprop"], "ordered": false}}], "values": {"units_1": 130, "units_2": 180, "units_3": 160, "optimizer": "rmsprop"}}, "metrics": {"metrics": {"loss": {"direction": "min", "observations": [{"value": [0.38720422983169556], "step": 12}]}, "val_loss": {"direction": "min", "observations": [{"value": [0.2151593565940857], "step": 12}]}}}, "score": 0.2151593565940857, "best_step": 12, "status": "COMPLETED", "message": null}