{"trial_id": "18", "hyperparameters": {"space": [{"class_name": "Int", "config": {"name": "units_1", "default": null, "conditions": [], "min_value": 50, "max_value": 200, "step": 10, "sampling": "linear"}}, {"class_name": "Int", "config": {"name": "units_2", "default": null, "conditions": [], "min_value": 50, "max_value": 200, "step": 10, "sampling": "linear"}}, {"class_name": "Int", "config": {"name": "units_3", "default": null, "conditions": [], "min_value": 50, "max_value": 200, "step": 10, "sampling": "linear"}}, {"class_name": "Choice", "config": {"name": "optimizer", "default": "adam", "conditions": [], "values": ["adam", "rmsprop"], "ordered": false}}], "values": {"units_1": 170, "units_2": 60, "units_3": 60, "optimizer": "adam"}}, "metrics": {"metrics": {"loss": {"direction": "min", "observations": [{"value": [5.900946617126465], "step": 2}]}, "val_loss": {"direction": "min", "observations": [{"value": [1.1312676668167114], "step": 2}]}}}, "score": 1.1312676668167114, "best_step": 2, "status": "COMPLETED", "message": null}