{"trial_id": "32", "hyperparameters": {"space": [{"class_name": "Int", "config": {"name": "units_1", "default": null, "conditions": [], "min_value": 16, "max_value": 64, "step": 16, "sampling": "linear"}}, {"class_name": "Int", "config": {"name": "units_2", "default": null, "conditions": [], "min_value": 16, "max_value": 64, "step": 16, "sampling": "linear"}}, {"class_name": "Int", "config": {"name": "units_3", "default": null, "conditions": [], "min_value": 16, "max_value": 64, "step": 16, "sampling": "linear"}}, {"class_name": "Choice", "config": {"name": "learning_rate", "default": 0.01, "conditions": [], "values": [0.01, 0.001, 0.0001], "ordered": true}}], "values": {"units_1": 64, "units_2": 32, "units_3": 48, "learning_rate": 0.01}}, "metrics": {"metrics": {"loss": {"direction": "min", "observations": [{"value": [0.6868869662284851], "step": 13}]}, "accuracy": {"direction": "max", "observations": [{"value": [0.5561848878860474], "step": 13}]}, "val_loss": {"direction": "min", "observations": [{"value": [0.684458315372467], "step": 13}]}, "val_accuracy": {"direction": "max", "observations": [{"value": [0.5724637508392334], "step": 13}]}}}, "score": 0.5724637508392334, "best_step": 13, "status": "COMPLETED", "message": null}